{
  "title": "Qazi Mustabeen Noor",
  "url": "https://rohanfaiyaz.com/",
  "repository": "https://github.com/rohanfaiyazkhan/elventy-blog-scratch",
  "language": "en",
  "description": "Developer cat. AI Apocalypse prevention enthusiast.",
  "social": {
    "github": "https://github.com/rohanfaiyazkhan",
    "twitter": "https://twitter.com/rohanfaiyaz",
    "dev": "https://dev.to/rohanfaiyaz",
    "linkedin": "https://linkedin.in/in/Mustabeen-faiyaz-khan",
    "email": "rohankhan170@gmail.com"
  },
  "feed": {
    "subtitle": "Developer cat. AI Apocalypse prevention enthusiast.",
    "filename": "feed.xml",
    "path": "/feed/feed.xml",
    "id": "https://rohanfaiyaz.com/"
  },
  "jsonfeed": {
    "path": "/feed/feed.json",
    "url": "https://rohanfaiyaz.com/feed/feed.json"
  },
  "author": {
    "name": "Qazi Mustabeen Noor",
    "email": "rohankhan170@gmail.com",
    "url": "https://rohanfaiyaz.com/"
  }
}
